biclustpy/__init__.py
biclustpy/ch.py
biclustpy/command_line.py
biclustpy/helpers.py
biclustpy/ilp.py
biclustpy/main.py
biclustpy-0.2.dist-info/LICENSE
biclustpy-0.2.dist-info/METADATA
biclustpy-0.2.dist-info/WHEEL
biclustpy-0.2.dist-info/entry_points.txt
biclustpy-0.2.dist-info/top_level.txt
biclustpy-0.2.dist-info/RECORD
